{
    "classes": [
        {
            "className": "GraphWidget",
            "lineNumber": 36,
            "object": true,
            "qualifiedClassName": "GraphWidget",
            "superClasses": [
                {
                    "access": "public",
                    "name": "QWidget"
                }
            ]
        },
        {
            "className": "LineGraphWindow",
            "lineNumber": 59,
            "object": true,
            "qualifiedClassName": "LineGraphWindow",
            "slots": [
                {
                    "access": "private",
                    "arguments": [
                        {
                            "name": "index",
                            "type": "int"
                        }
                    ],
                    "index": 0,
                    "lineNumber": 73,
                    "name": "onMetricChanged",
                    "returnType": "void"
                },
                {
                    "access": "private",
                    "arguments": [
                        {
                            "name": "response",
                            "type": "QString"
                        }
                    ],
                    "index": 1,
                    "lineNumber": 74,
                    "name": "onApiResponse",
                    "returnType": "void"
                },
                {
                    "access": "private",
                    "arguments": [
                        {
                            "name": "error",
                            "type": "QString"
                        }
                    ],
                    "index": 2,
                    "lineNumber": 75,
                    "name": "onApiError",
                    "returnType": "void"
                },
                {
                    "access": "private",
                    "index": 3,
                    "lineNumber": 76,
                    "name": "fetchPacketData",
                    "returnType": "void"
                }
            ],
            "superClasses": [
                {
                    "access": "public",
                    "name": "QWidget"
                }
            ]
        }
    ],
    "inputFile": "linegraphwindow.h",
    "outputRevision": 69
}
